<?xml version="1.0" encoding="UTF-8"?>
<objects serializationModel="Studio.02.02.00">
	<object class="AudioFile" id="{1dbf3887-5d65-49fe-94bd-533d1a48d668}">
		<property name="assetPath">
			<value>enemy voice-013.wav</value>
		</property>
		<property name="frequencyInKHz">
			<value>48</value>
		</property>
		<property name="channelCount">
			<value>1</value>
		</property>
		<property name="length">
			<value>1.0585833333333334</value>
		</property>
		<relationship name="masterAssetFolder">
			<destination>{a0822710-cead-4033-93a8-0ecaacb0b3a8}</destination>
		</relationship>
	</object>
</objects>
