<?xml version="1.0" encoding="UTF-8"?>
<objects serializationModel="Studio.02.02.00">
	<object class="AudioFile" id="{8f3433ae-ca92-4bab-a2ac-774e72313736}">
		<property name="assetPath">
			<value>footsteps-004.wav</value>
		</property>
		<property name="frequencyInKHz">
			<value>48</value>
		</property>
		<property name="channelCount">
			<value>1</value>
		</property>
		<property name="length">
			<value>0.18177083333333333</value>
		</property>
		<relationship name="masterAssetFolder">
			<destination>{a0822710-cead-4033-93a8-0ecaacb0b3a8}</destination>
		</relationship>
	</object>
</objects>
